flask_blueprints/__init__.py
flask_blueprints-0.0.6.dist-info/LICENSE
flask_blueprints-0.0.6.dist-info/METADATA
flask_blueprints-0.0.6.dist-info/WHEEL
flask_blueprints-0.0.6.dist-info/top_level.txt
flask_blueprints-0.0.6.dist-info/RECORD
