Metadata-Version: 2.1
Name: flask-blueprints
Version: 0.0.6
Summary: Import and register all Flask Blueprints (including nested) from a package directory.
Author-email: Damien Bezborodov <dbezborodov@gmail.com>
Project-URL: Homepage, https://github.com/bezborodow/flask-blueprints
Project-URL: Bug Tracker, https://github.com/bezborodow/flask-blueprints/issues
Classifier: Programming Language :: Python :: 3
Classifier: License :: OSI Approved :: BSD License
Classifier: Operating System :: OS Independent
Classifier: Framework :: Flask
Requires-Python: >=3.7
License-File: LICENSE
